AUTHORS.md
LICENSE
README.md
setup.py
fcapsy_experiments/__init__.py
fcapsy_experiments/_styles.py
fcapsy_experiments/correlation_table.py
fcapsy_experiments/correlations_box_plot.py
fcapsy_experiments.egg-info/PKG-INFO
fcapsy_experiments.egg-info/SOURCES.txt
fcapsy_experiments.egg-info/dependency_links.txt
fcapsy_experiments.egg-info/requires.txt
fcapsy_experiments.egg-info/top_level.txt
fcapsy_experiments/centrality/__init__.py
fcapsy_experiments/centrality/centrality.py
fcapsy_experiments/mca/__init__.py
fcapsy_experiments/mca/mca_concept.py
fcapsy_experiments/typicality/__init__.py
fcapsy_experiments/typicality/concept_typicality.py
fcapsy_experiments/typicality/top_r_similarity.py
tests/__init__.py
tests/typicality/__init__.py
tests/typicality/test_top_k_similarity.py