Metadata-Version: 2.1
Name: fcapsy-experiments
Version: 0.2.5
Summary: Package of experiments for fcapsy library.
Home-page: https://github.com/mikulatomas/fcapsy_experiments
Author: Tomáš Mikula
Author-email: mail@tomasmikula.cz
License: MIT license
Keywords: fca formal concept analysis experiments
Platform: UNKNOWN
Classifier: Development Status :: 2 - Pre-Alpha
Classifier: Intended Audience :: Science/Research
Classifier: License :: OSI Approved :: MIT License
Classifier: Natural Language :: English
Classifier: Programming Language :: Python :: 3
Classifier: Programming Language :: Python :: 3.7
Classifier: Programming Language :: Python :: 3.8
Classifier: Programming Language :: Python :: 3.9
Classifier: Programming Language :: Python :: 3.10
Requires-Python: >=3.7
